{
  "book": "mt",
  "bookName": "Mateus",
  "chapter": 15,
  "verses": [
    {
      "chapter": 15,
      "verse": 1,
      "text": "Então, vieram de Jerusalém a Jesus alguns fariseus e escribas e perguntaram:"
    },
    {
      "chapter": 15,
      "verse": 2,
      "text": "Por que transgridem os teus discípulos a tradição dos anciãos? Pois não lavam as mãos, quando comem."
    },
    {
      "chapter": 15,
      "verse": 3,
      "text": "Ele, porém, lhes respondeu: Por que transgredis vós também o mandamento de Deus, por causa da vossa tradição?"
    },
    {
      "chapter": 15,
      "verse": 4,
      "text": "Porque Deus ordenou: Honra a teu pai e a tua mãe; e: Quem maldisser a seu pai ou a sua mãe seja punido de morte."
    },
    {
      "chapter": 15,
      "verse": 5,
      "text": "Mas vós dizeis: Se alguém disser a seu pai ou a sua mãe: É oferta ao Senhor aquilo que poderias aproveitar de mim;"
    },
    {
      "chapter": 15,
      "verse": 6,
      "text": "esse jamais honrará a seu pai ou a sua mãe. E, assim, invalidastes a palavra de Deus, por causa da vossa tradição."
    },
    {
      "chapter": 15,
      "verse": 7,
      "text": "Hipócritas! Bem profetizou Isaías a vosso respeito, dizendo:"
    },
    {
      "chapter": 15,
      "verse": 8,
      "text": "Este povo honra-me com os lábios, mas o seu coração está longe de mim."
    },
    {
      "chapter": 15,
      "verse": 9,
      "text": "E em vão me adoram, ensinando doutrinas que são preceitos de homens."
    },
    {
      "chapter": 15,
      "verse": 10,
      "text": "E, tendo convocado a multidão, lhes disse: Ouvi e entendei:"
    },
    {
      "chapter": 15,
      "verse": 11,
      "text": "não é o que entra pela boca o que contamina o homem, mas o que sai da boca, isto, sim, contamina o homem."
    },
    {
      "chapter": 15,
      "verse": 12,
      "text": "Então, aproximando-se dele os discípulos, disseram: Sabes que os fariseus, ouvindo a tua palavra, se escandalizaram?"
    },
    {
      "chapter": 15,
      "verse": 13,
      "text": "Ele, porém, respondeu: Toda planta que meu Pai celestial não plantou será arrancada."
    },
    {
      "chapter": 15,
      "verse": 14,
      "text": "Deixai-os; são cegos, guias de cegos. Ora, se um cego guiar outro cego, cairão ambos no barranco."
    },
    {
      "chapter": 15,
      "verse": 15,
      "text": "Então, lhe disse Pedro: Explica-nos a parábola."
    },
    {
      "chapter": 15,
      "verse": 16,
      "text": "Jesus, porém, disse: Também vós não entendeis ainda?"
    },
    {
      "chapter": 15,
      "verse": 17,
      "text": "Não compreendeis que tudo o que entra pela boca desce para o ventre e, depois, é lançado em lugar escuso?"
    },
    {
      "chapter": 15,
      "verse": 18,
      "text": "Mas o que sai da boca vem do coração, e é isso que contamina o homem."
    },
    {
      "chapter": 15,
      "verse": 19,
      "text": "Porque do coração procedem maus desígnios, homicídios, adultérios, prostituição, furtos, falsos testemunhos, blasfêmias."
    },
    {
      "chapter": 15,
      "verse": 20,
      "text": "São estas as coisas que contaminam o homem; mas o comer sem lavar as mãos não o contamina."
    },
    {
      "chapter": 15,
      "verse": 21,
      "text": "Partindo Jesus dali, retirou-se para os lados de Tiro e Sidom."
    },
    {
      "chapter": 15,
      "verse": 22,
      "text": "E eis que uma mulher cananeia, que viera daquelas regiões, clamava: Senhor, Filho de Davi, tem compaixão de mim! Minha filha está horrivelmente endemoninhada."
    },
    {
      "chapter": 15,
      "verse": 23,
      "text": "Ele, porém, não lhe respondeu palavra. E os seus discípulos, aproximando-se, rogaram-lhe: Despede-a, pois vem clamando atrás de nós."
    },
    {
      "chapter": 15,
      "verse": 24,
      "text": "Mas Jesus respondeu: Não fui enviado senão às ovelhas perdidas da casa de Israel."
    },
    {
      "chapter": 15,
      "verse": 25,
      "text": "Ela, porém, veio e o adorou, dizendo: Senhor, socorre-me!"
    },
    {
      "chapter": 15,
      "verse": 26,
      "text": "Então, ele, respondendo, disse: Não é bom tomar o pão dos filhos e lançá-lo aos cachorrinhos."
    },
    {
      "chapter": 15,
      "verse": 27,
      "text": "Ela, contudo, replicou: Sim, Senhor, porém os cachorrinhos comem das migalhas que caem da mesa dos seus donos."
    },
    {
      "chapter": 15,
      "verse": 28,
      "text": "Então, lhe disse Jesus: Ó mulher, grande é a tua fé! Faça-se contigo como queres. E, desde aquele momento, sua filha ficou sã."
    },
    {
      "chapter": 15,
      "verse": 29,
      "text": "Partindo Jesus dali, foi para junto do mar da Galileia; e, subindo ao monte, assentou-se ali."
    },
    {
      "chapter": 15,
      "verse": 30,
      "text": "E vieram a ele muitas multidões trazendo consigo coxos, aleijados, cegos, mudos e outros muitos e os largaram junto aos pés de Jesus; e ele os curou."
    },
    {
      "chapter": 15,
      "verse": 31,
      "text": "De modo que o povo se maravilhou ao ver que os mudos falavam, os aleijados recobravam saúde, os coxos andavam e os cegos viam. Então, glorificavam ao Deus de Israel."
    },
    {
      "chapter": 15,
      "verse": 32,
      "text": "E, chamando Jesus os seus discípulos, disse: Tenho compaixão desta gente, porque há três dias que permanece comigo e não tem o que comer; e não quero despedi-la em jejum, para que não desfaleça pelo caminho."
    },
    {
      "chapter": 15,
      "verse": 33,
      "text": "Mas os discípulos lhe disseram: Onde haverá neste deserto tantos pães para fartar tão grande multidão?"
    },
    {
      "chapter": 15,
      "verse": 34,
      "text": "Perguntou-lhes Jesus: Quantos pães tendes? Responderam: Sete e alguns peixinhos."
    },
    {
      "chapter": 15,
      "verse": 35,
      "text": "Então, tendo mandado o povo assentar-se no chão,"
    },
    {
      "chapter": 15,
      "verse": 36,
      "text": "tomou os sete pães e os peixes, e, dando graças, partiu, e deu aos discípulos, e estes, ao povo."
    },
    {
      "chapter": 15,
      "verse": 37,
      "text": "Todos comeram e se fartaram; e, do que sobejou, recolheram sete cestos cheios."
    },
    {
      "chapter": 15,
      "verse": 38,
      "text": "Ora, os que comeram eram quatro mil homens, além de mulheres e crianças."
    },
    {
      "chapter": 15,
      "verse": 39,
      "text": "E, tendo despedido as multidões, entrou Jesus no barco e foi para o território de Magadã."
    }
  ]
}