{
  "book": "mt",
  "bookName": "Mateus",
  "chapter": 16,
  "verses": [
    {
      "chapter": 16,
      "verse": 1,
      "text": "Aproximando-se os fariseus e os saduceus, tentando-o, pediram-lhe que lhes mostrasse um sinal vindo do céu."
    },
    {
      "chapter": 16,
      "verse": 2,
      "text": "Ele, porém, lhes respondeu: Chegada a tarde, dizeis: Haverá bom tempo, porque o céu está avermelhado;"
    },
    {
      "chapter": 16,
      "verse": 3,
      "text": "e, pela manhã: Hoje, haverá tempestade, porque o céu está de um vermelho sombrio. Sabeis, na verdade, discernir o aspecto do céu e não podeis discernir os sinais dos tempos?"
    },
    {
      "chapter": 16,
      "verse": 4,
      "text": "Uma geração má e adúltera pede um sinal; e nenhum sinal lhe será dado, senão o de Jonas. E, deixando-os, retirou-se."
    },
    {
      "chapter": 16,
      "verse": 5,
      "text": "Ora, tendo os discípulos passado para o outro lado, esqueceram-se de levar pão."
    },
    {
      "chapter": 16,
      "verse": 6,
      "text": "E Jesus lhes disse: Vede e acautelai-vos do fermento dos fariseus e dos saduceus."
    },
    {
      "chapter": 16,
      "verse": 7,
      "text": "Eles, porém, discorriam entre si, dizendo: É porque não trouxemos pão."
    },
    {
      "chapter": 16,
      "verse": 8,
      "text": "Percebendo-o Jesus, disse: Por que discorreis entre vós, homens de pequena fé, sobre o não terdes pão?"
    },
    {
      "chapter": 16,
      "verse": 9,
      "text": "Não compreendeis ainda, nem vos lembrais dos cinco pães para cinco mil homens e de quantos cestos tomastes?"
    },
    {
      "chapter": 16,
      "verse": 10,
      "text": "Nem dos sete pães para os quatro mil e de quantos cestos tomastes?"
    },
    {
      "chapter": 16,
      "verse": 11,
      "text": "Como não compreendeis que não vos falei a respeito de pães? E sim: acautelai-vos do fermento dos fariseus e dos saduceus."
    },
    {
      "chapter": 16,
      "verse": 12,
      "text": "Então, entenderam que não lhes dissera que se acautelassem do fermento de pães, mas da doutrina dos fariseus e dos saduceus."
    },
    {
      "chapter": 16,
      "verse": 13,
      "text": "Indo Jesus para os lados de Cesareia de Filipe, perguntou a seus discípulos: Quem diz o povo ser o Filho do Homem?"
    },
    {
      "chapter": 16,
      "verse": 14,
      "text": "E eles responderam: Uns dizem: João Batista; outros: Elias; e outros: Jeremias ou algum dos profetas."
    },
    {
      "chapter": 16,
      "verse": 15,
      "text": "Mas vós, continuou ele, quem dizeis que eu sou?"
    },
    {
      "chapter": 16,
      "verse": 16,
      "text": "Respondendo Simão Pedro, disse: Tu és o Cristo, o Filho do Deus vivo."
    },
    {
      "chapter": 16,
      "verse": 17,
      "text": "Então, Jesus lhe afirmou: Bem-aventurado és, Simão Barjonas, porque não foi carne e sangue que to revelaram, mas meu Pai, que está nos céus."
    },
    {
      "chapter": 16,
      "verse": 18,
      "text": "Também eu te digo que tu és Pedro, e sobre esta pedra edificarei a minha igreja, e as portas do inferno não prevalecerão contra ela."
    },
    {
      "chapter": 16,
      "verse": 19,
      "text": "Dar-te-ei as chaves do reino dos céus; o que ligares na terra terá sido ligado nos céus; e o que desligares na terra terá sido desligado nos céus."
    },
    {
      "chapter": 16,
      "verse": 20,
      "text": "Então, advertiu os discípulos de que a ninguém dissessem ser ele o Cristo."
    },
    {
      "chapter": 16,
      "verse": 21,
      "text": "Desde esse tempo, começou Jesus Cristo a mostrar a seus discípulos que lhe era necessário seguir para Jerusalém e sofrer muitas coisas dos anciãos, dos principais sacerdotes e dos escribas, ser morto e ressuscitado no terceiro dia."
    },
    {
      "chapter": 16,
      "verse": 22,
      "text": "E Pedro, chamando-o à parte, começou a reprová-lo, dizendo: Tem compaixão de ti, Senhor; isso de modo algum te acontecerá."
    },
    {
      "chapter": 16,
      "verse": 23,
      "text": "Mas Jesus, voltando-se, disse a Pedro: Arreda, Satanás! Tu és para mim pedra de tropeço, porque não cogitas das coisas de Deus, e sim das dos homens."
    },
    {
      "chapter": 16,
      "verse": 24,
      "text": "Então, disse Jesus a seus discípulos: Se alguém quer vir após mim, a si mesmo se negue, tome a sua cruz e siga-me."
    },
    {
      "chapter": 16,
      "verse": 25,
      "text": "Porquanto, quem quiser salvar a sua vida perdê-la-á; e quem perder a vida por minha causa achá-la-á."
    },
    {
      "chapter": 16,
      "verse": 26,
      "text": "Pois que aproveitará o homem se ganhar o mundo inteiro e perder a sua alma? Ou que dará o homem em troca da sua alma?"
    },
    {
      "chapter": 16,
      "verse": 27,
      "text": "Porque o Filho do Homem há de vir na glória de seu Pai, com os seus anjos, e, então, retribuirá a cada um conforme as suas obras."
    },
    {
      "chapter": 16,
      "verse": 28,
      "text": "Em verdade vos digo que alguns há, dos que aqui se encontram, que de maneira nenhuma passarão pela morte até que vejam vir o Filho do Homem no seu reino."
    }
  ]
}