{
  "book": "dt",
  "bookName": "Deuteronômio",
  "chapter": 19,
  "verses": [
    {
      "chapter": 19,
      "verse": 1,
      "text": "Quando o SENHOR, teu Deus, eliminar as nações cuja terra te dará o SENHOR, teu Deus, e as desapossares e morares nas suas cidades e nas suas casas,"
    },
    {
      "chapter": 19,
      "verse": 2,
      "text": "três cidades separarás no meio da tua terra que te dará o SENHOR, teu Deus, para a possuíres."
    },
    {
      "chapter": 19,
      "verse": 3,
      "text": "Preparar-te-ás o caminho e os limites da tua terra que te fará possuir o SENHOR, teu Deus, dividirás em três; e isto será para que nelas se acolha todo homicida."
    },
    {
      "chapter": 19,
      "verse": 4,
      "text": "Este é o caso tocante ao homicida que nelas se acolher, para que viva: aquele que, sem o querer, ferir o seu próximo, a quem não aborrecia dantes."
    },
    {
      "chapter": 19,
      "verse": 5,
      "text": "Assim, aquele que entrar com o seu próximo no bosque, para cortar lenha, e, manejando com impulso o machado para cortar a árvore, o ferro saltar do cabo e atingir o seu próximo, e este morrer, o tal se acolherá em uma destas cidades e viverá;"
    },
    {
      "chapter": 19,
      "verse": 6,
      "text": "para que o vingador do sangue não persiga o homicida, quando se lhe enfurecer o coração, e o alcance, por ser comprido o caminho, e lhe tire a vida, porque não é culpado de morte, pois não o aborrecia dantes."
    },
    {
      "chapter": 19,
      "verse": 7,
      "text": "Portanto, te ordeno: três cidades separarás."
    },
    {
      "chapter": 19,
      "verse": 8,
      "text": "Se o SENHOR, teu Deus, dilatar os teus limites, como jurou a teus pais, e te der toda a terra que lhes prometeu,"
    },
    {
      "chapter": 19,
      "verse": 9,
      "text": "desde que guardes todos estes mandamentos que hoje te ordeno, para cumpri-los, amando o SENHOR, teu Deus, e andando nos seus caminhos todos os dias, então, acrescentarás outras três cidades além destas três,"
    },
    {
      "chapter": 19,
      "verse": 10,
      "text": "para que o sangue inocente se não derrame no meio da tua terra que o SENHOR, teu Deus, te dá por herança, pois haveria sangue sobre ti."
    },
    {
      "chapter": 19,
      "verse": 11,
      "text": "Mas, havendo alguém que aborrece a seu próximo, e lhe arma ciladas, e se levanta contra ele, e o fere de golpe mortal, e se acolhe em uma dessas cidades,"
    },
    {
      "chapter": 19,
      "verse": 12,
      "text": "os anciãos da sua cidade enviarão a tirá-lo dali e a entregá-lo na mão do vingador do sangue, para que morra."
    },
    {
      "chapter": 19,
      "verse": 13,
      "text": "Não o olharás com piedade; antes, exterminarás de Israel a culpa do sangue inocente, para que te vá bem."
    },
    {
      "chapter": 19,
      "verse": 14,
      "text": "Não mudes os marcos do teu próximo, que os antigos fixaram na tua herança, na terra que o SENHOR, teu Deus, te dá para a possuíres."
    },
    {
      "chapter": 19,
      "verse": 15,
      "text": "Uma só testemunha não se levantará contra alguém por qualquer iniquidade ou por qualquer pecado, seja qual for que cometer; pelo depoimento de duas ou três testemunhas, se estabelecerá o fato."
    },
    {
      "chapter": 19,
      "verse": 16,
      "text": "Quando se levantar testemunha falsa contra alguém, para o acusar de algum transvio,"
    },
    {
      "chapter": 19,
      "verse": 17,
      "text": "então, os dois homens que tiverem a demanda se apresentarão perante o SENHOR, diante dos sacerdotes e dos juízes que houver naqueles dias."
    },
    {
      "chapter": 19,
      "verse": 18,
      "text": "Os juízes indagarão bem; se a testemunha for falsa e tiver testemunhado falsamente contra seu irmão,"
    },
    {
      "chapter": 19,
      "verse": 19,
      "text": "far-lhe-eis como cuidou fazer a seu irmão; e, assim, exterminarás o mal do meio de ti;"
    },
    {
      "chapter": 19,
      "verse": 20,
      "text": "para que os que ficarem o ouçam, e temam, e nunca mais tornem a fazer semelhante mal no meio de ti."
    },
    {
      "chapter": 19,
      "verse": 21,
      "text": "Não o olharás com piedade: vida por vida, olho por olho, dente por dente, mão por mão, pé por pé."
    }
  ]
}