{
  "book": "act",
  "bookName": "Atos",
  "chapter": 20,
  "verses": [
    {
      "chapter": 20,
      "verse": 1,
      "text": "Cessado o tumulto, Paulo mandou chamar os discípulos, e, tendo-os confortado, despediu-se, e partiu para a Macedônia."
    },
    {
      "chapter": 20,
      "verse": 2,
      "text": "Havendo atravessado aquelas terras, fortalecendo os discípulos com muitas exortações, dirigiu-se para a Grécia,"
    },
    {
      "chapter": 20,
      "verse": 3,
      "text": "onde se demorou três meses. Tendo havido uma conspiração por parte dos judeus contra ele, quando estava para embarcar rumo à Síria, determinou voltar pela Macedônia."
    },
    {
      "chapter": 20,
      "verse": 4,
      "text": "Acompanharam-no [até à Ásia] Sópatro, de Bereia, filho de Pirro, Aristarco e Secundo, de Tessalônica, Gaio, de Derbe, e Timóteo, bem como Tíquico e Trófimo, da Ásia;"
    },
    {
      "chapter": 20,
      "verse": 5,
      "text": "estes nos precederam, esperando-nos em Trôade."
    },
    {
      "chapter": 20,
      "verse": 6,
      "text": "Depois dos dias dos pães asmos, navegamos de Filipos e, em cinco dias, fomos ter com eles naquele porto, onde passamos uma semana."
    },
    {
      "chapter": 20,
      "verse": 7,
      "text": "No primeiro dia da semana, estando nós reunidos com o fim de partir o pão, Paulo, que devia seguir viagem no dia imediato, exortava-os e prolongou o discurso até à meia-noite."
    },
    {
      "chapter": 20,
      "verse": 8,
      "text": "Havia muitas lâmpadas no cenáculo onde estávamos reunidos."
    },
    {
      "chapter": 20,
      "verse": 9,
      "text": "Um jovem, chamado Êutico, que estava sentado numa janela, adormecendo profundamente durante o prolongado discurso de Paulo, vencido pelo sono, caiu do terceiro andar abaixo e foi levantado morto."
    },
    {
      "chapter": 20,
      "verse": 10,
      "text": "Descendo, porém, Paulo inclinou-se sobre ele e, abraçando-o, disse: Não vos perturbeis, que a vida nele está."
    },
    {
      "chapter": 20,
      "verse": 11,
      "text": "Subindo de novo, partiu o pão, e comeu, e ainda lhes falou largamente até ao romper da alva. E, assim, partiu."
    },
    {
      "chapter": 20,
      "verse": 12,
      "text": "Então, conduziram vivo o rapaz e sentiram-se grandemente confortados."
    },
    {
      "chapter": 20,
      "verse": 13,
      "text": "Nós, porém, prosseguindo, embarcamos e navegamos para Assôs, onde devíamos receber Paulo, porque assim nos fora determinado, devendo ele ir por terra."
    },
    {
      "chapter": 20,
      "verse": 14,
      "text": "Quando se reuniu conosco em Assôs, recebemo-lo a bordo e fomos a Mitilene;"
    },
    {
      "chapter": 20,
      "verse": 15,
      "text": "dali, navegando, no dia seguinte, passamos defronte de Quios, no dia imediato, tocamos em Samos e, um dia depois, chegamos a Mileto."
    },
    {
      "chapter": 20,
      "verse": 16,
      "text": "Porque Paulo já havia determinado não aportar em Éfeso, não querendo demorar-se na Ásia, porquanto se apressava com o intuito de passar o dia de Pentecostes em Jerusalém, caso lhe fosse possível."
    },
    {
      "chapter": 20,
      "verse": 17,
      "text": "De Mileto, mandou a Éfeso chamar os presbíteros da igreja."
    },
    {
      "chapter": 20,
      "verse": 18,
      "text": "E, quando se encontraram com ele, disse-lhes: Vós bem sabeis como foi que me conduzi entre vós em todo o tempo, desde o primeiro dia em que entrei na Ásia,"
    },
    {
      "chapter": 20,
      "verse": 19,
      "text": "servindo ao Senhor com toda a humildade, lágrimas e provações que, pelas ciladas dos judeus, me sobrevieram,"
    },
    {
      "chapter": 20,
      "verse": 20,
      "text": "jamais deixando de vos anunciar coisa alguma proveitosa e de vo-la ensinar publicamente e também de casa em casa,"
    },
    {
      "chapter": 20,
      "verse": 21,
      "text": "testificando tanto a judeus como a gregos o arrependimento para com Deus e a fé em nosso Senhor Jesus [Cristo]."
    },
    {
      "chapter": 20,
      "verse": 22,
      "text": "E, agora, constrangido em meu espírito, vou para Jerusalém, não sabendo o que ali me acontecerá,"
    },
    {
      "chapter": 20,
      "verse": 23,
      "text": "senão que o Espírito Santo, de cidade em cidade, me assegura que me esperam cadeias e tribulações."
    },
    {
      "chapter": 20,
      "verse": 24,
      "text": "Porém em nada considero a vida preciosa para mim mesmo, contanto que complete a minha carreira e o ministério que recebi do Senhor Jesus para testemunhar o evangelho da graça de Deus."
    },
    {
      "chapter": 20,
      "verse": 25,
      "text": "Agora, eu sei que todos vós, em cujo meio passei pregando o reino, não vereis mais o meu rosto."
    },
    {
      "chapter": 20,
      "verse": 26,
      "text": "Portanto, eu vos protesto, no dia de hoje, que estou limpo do sangue de todos;"
    },
    {
      "chapter": 20,
      "verse": 27,
      "text": "porque jamais deixei de vos anunciar todo o desígnio de Deus."
    },
    {
      "chapter": 20,
      "verse": 28,
      "text": "Atendei por vós e por todo o rebanho sobre o qual o Espírito Santo vos constituiu bispos, para pastoreardes a igreja de Deus, a qual ele comprou com o seu próprio sangue."
    },
    {
      "chapter": 20,
      "verse": 29,
      "text": "Eu sei que, depois da minha partida, entre vós penetrarão lobos vorazes, que não pouparão o rebanho."
    },
    {
      "chapter": 20,
      "verse": 30,
      "text": "E que, dentre vós mesmos, se levantarão homens falando coisas pervertidas para arrastar os discípulos atrás deles."
    },
    {
      "chapter": 20,
      "verse": 31,
      "text": "Portanto, vigiai, lembrando-vos de que, por três anos, noite e dia, não cessei de admoestar, com lágrimas, a cada um."
    },
    {
      "chapter": 20,
      "verse": 32,
      "text": "Agora, pois, encomendo-vos ao Senhor e à palavra da sua graça, que tem poder para vos edificar e dar herança entre todos os que são santificados."
    },
    {
      "chapter": 20,
      "verse": 33,
      "text": "De ninguém cobicei prata, nem ouro, nem vestes;"
    },
    {
      "chapter": 20,
      "verse": 34,
      "text": "vós mesmos sabeis que estas mãos serviram para o que me era necessário a mim e aos que estavam comigo."
    },
    {
      "chapter": 20,
      "verse": 35,
      "text": "Tenho-vos mostrado em tudo que, trabalhando assim, é mister socorrer os necessitados e recordar as palavras do próprio Senhor Jesus: Mais bem-aventurado é dar que receber."
    },
    {
      "chapter": 20,
      "verse": 36,
      "text": "Tendo dito estas coisas, ajoelhando-se, orou com todos eles."
    },
    {
      "chapter": 20,
      "verse": 37,
      "text": "Então, houve grande pranto entre todos, e, abraçando afetuosamente a Paulo, o beijavam,"
    },
    {
      "chapter": 20,
      "verse": 38,
      "text": "entristecidos especialmente pela palavra que ele dissera: que não mais veriam o seu rosto. E acompanharam-no até ao navio."
    }
  ]
}